LICENSE
MANIFEST.in
README.md
setup.cfg
setup.py
tap_swellrewards/__init__.py
tap_swellrewards/streams.py
tap_swellrewards.egg-info/PKG-INFO
tap_swellrewards.egg-info/SOURCES.txt
tap_swellrewards.egg-info/dependency_links.txt
tap_swellrewards.egg-info/entry_points.txt
tap_swellrewards.egg-info/requires.txt
tap_swellrewards.egg-info/top_level.txt
tap_swellrewards/schemas/customers.json