Metadata-Version: 1.1
Name: tap-swellrewards
Version: 0.1.6
Summary: Singer.io tap for extracting data from Swell Rewards API
Home-page: http://singer.io
Author: Stitch
Author-email: UNKNOWN
License: UNKNOWN
Platform: UNKNOWN
Classifier: Programming Language :: Python :: 3 :: Only
